setup.py
coding_chaska_package/__init__.py
coding_chaska_package/module1.py
coding_chaska_package.egg-info/PKG-INFO
coding_chaska_package.egg-info/SOURCES.txt
coding_chaska_package.egg-info/dependency_links.txt
coding_chaska_package.egg-info/top_level.txt