Metadata-Version: 2.1
Name: coding-chaska-package
Version: 0.1
Summary: An example of a python package from pre-existing code
Author: Rohit Maurya
Author-email: codingchaska.info@gmail.com
License: MIT
